pydicom_ext/ConcFormatUtils.py
pydicom_ext/Utils.py
pydicom_ext/VtkDataUtils.py
pydicom_ext/__init__.py
pydicom_ext/pydicom_series.py
pydicom_ext-0.6.1.dist-info/METADATA
pydicom_ext-0.6.1.dist-info/RECORD
pydicom_ext-0.6.1.dist-info/WHEEL
pydicom_ext-0.6.1.dist-info/top_level.txt
