Metadata-Version: 2.1
Name: pydicom-ext
Version: 0.6.1
Summary: Additional functions for dicom data manipulation
Home-page: https://github.com/shinaji/pydicom_ext
Author: shinaji
Author-email: shina.synergy@gmail.com
License: MIT
Keywords: dicom python medical imaging
Platform: UNKNOWN
Classifier: License :: OSI Approved :: MIT License
Classifier: Intended Audience :: Developers
Classifier: Intended Audience :: Healthcare Industry
Classifier: Intended Audience :: Science/Research
Classifier: Development Status :: 5 - Production/Stable
Classifier: Programming Language :: Python
Classifier: Programming Language :: Python :: 3.6
Classifier: Operating System :: OS Independent
Classifier: Topic :: Scientific/Engineering :: Medical Science Apps.
Classifier: Topic :: Scientific/Engineering :: Physics
Classifier: Topic :: Software Development :: Libraries
